gerg/__init__.py
gerg/agent.py
gerg/cli.py
gerg/config.py
gerg/safety.py
gerg/utils.py
gerg-0.0.1.dist-info/licenses/LICENSE
gerg-0.0.1.dist-info/METADATA
gerg-0.0.1.dist-info/WHEEL
gerg-0.0.1.dist-info/entry_points.txt
gerg-0.0.1.dist-info/top_level.txt
gerg-0.0.1.dist-info/RECORD
