Metadata-Version: 2.4
Name: gerg
Version: 0.0.1
Summary: CLI agent that collaborates with you by planning and running shell commands via a local Ollama model
Author: Greg Gottlieb
License: MIT
Project-URL: Homepage, https://github.com/ggottli/gerg
Keywords: ollama,cli,agent,shell,automation
Classifier: Programming Language :: Python :: 3
Classifier: License :: OSI Approved :: MIT License
Classifier: Operating System :: OS Independent
Requires-Python: >=3.9
License-File: LICENSE
Requires-Dist: requests>=2.31.0
Requires-Dist: tomli; python_version < "3.11"
Dynamic: license-file
